ubxtranslator/__init__.py
ubxtranslator/core.py
ubxtranslator/predefined.py
ubxtranslator-0.2.5.dist-info/LICENSE
ubxtranslator-0.2.5.dist-info/METADATA
ubxtranslator-0.2.5.dist-info/WHEEL
ubxtranslator-0.2.5.dist-info/top_level.txt
ubxtranslator-0.2.5.dist-info/RECORD
