Metadata-Version: 2.1
Name: ubxtranslator
Version: 0.2.5
Summary: A lightweight python library for translating UBX packets
Home-page: http://github.com/dalymople/ubxtranslator
Author: Dalymople
Author-email: dalymople@gmail.com
License: GNU GPL v3
Classifier: Development Status :: 3 - Alpha
Classifier: License :: OSI Approved :: GNU General Public License v3 (GPLv3)
Classifier: Programming Language :: Python :: 3
Classifier: Topic :: Communications
License-File: LICENSE
